git_croissant/__init__.py
git_croissant/cli.py
git_croissant/commands/__init__.py
git_croissant/commands/clone.py
git_croissant/commands/pousse.py
git_croissant/commands/tire.py
git_croissant-0.0.1.dist-info/entry_points.txt
git_croissant-0.0.1.dist-info/WHEEL
git_croissant-0.0.1.dist-info/METADATA
git_croissant-0.0.1.dist-info/RECORD
