Metadata-Version: 2.1
Name: git-croissant
Version: 0.0.1
Summary: French Git CLI to respect the Toubon Law in France.
License: AGPL-3.0-or-later
Author: Christophe Benz
Author-email: christophe.benz@gmail.com
Requires-Python: >=3.10,<4.0
Classifier: License :: OSI Approved :: GNU Affero General Public License v3 or later (AGPLv3+)
Classifier: Programming Language :: Python :: 3
Classifier: Programming Language :: Python :: 3.10
Classifier: Programming Language :: Python :: 3.11
Requires-Dist: typer[all] (>=0.7.0,<0.8.0)
